elo_mmr_py/elo_mmr_python_bindings.cpython-311-darwin.so
elo_mmr_py/__init__.py
q_elo_mmr_py-1.0.2.dist-info/RECORD
q_elo_mmr_py-1.0.2.dist-info/WHEEL
q_elo_mmr_py-1.0.2.dist-info/top_level.txt
q_elo_mmr_py-1.0.2.dist-info/METADATA
q_elo_mmr_py-1.0.2.dist-info/licenses/LICENSE
rust/lib.rs
