Metadata-Version: 2.4
Name: q-elo-mmr-py
Version: 1.0.2
Summary: Python bindings for Elo-MRR
License-File: LICENSE
Dynamic: license-file
